jupyter_kernel_addons-0.1.2.dist-info/licenses/LICENSE
jupyter_kernel_handler/__init__.py
jupyter_printer/__init__.py
jupyter_kernel_addons-0.1.2.dist-info/METADATA
jupyter_kernel_addons-0.1.2.dist-info/WHEEL
jupyter_kernel_addons-0.1.2.dist-info/top_level.txt
jupyter_kernel_addons-0.1.2.dist-info/RECORD
