Metadata-Version: 2.4
Name: jupyter_kernel_addons
Version: 0.1.2
Summary: Jupyter Kernel Addons: Cell Execution Monitor with colored output and custom hooks
Home-page: https://github.com/Dataxcelerator/jupyter_kernel_addons
Author: Dataxcelerator
Author-email: opensource@dataxcelerator.com
License: MIT
Classifier: Programming Language :: Python :: 3
Classifier: License :: OSI Approved :: MIT License
Classifier: Operating System :: OS Independent
Requires-Python: >=3.7
License-File: LICENSE
Requires-Dist: ipython
Requires-Dist: jupyter
Dynamic: author
Dynamic: author-email
Dynamic: classifier
Dynamic: description
Dynamic: description-content-type
Dynamic: home-page
Dynamic: license
Dynamic: license-file
Dynamic: requires-dist
Dynamic: requires-python
Dynamic: summary
